commons_lib/README.md
commons_lib/__init__.py
commons_lib/models/__init__.py
commons_lib/models/entities/__init__.py
commons_lib/models/entities/appreciatation.py
commons_lib/models/entities/appreciatation_entity.py
commons_lib/models/entities/base_entity.py
commons_lib/models/entities/accounts/__init__.py
commons_lib/models/entities/accounts/account_category_entity.py
commons_lib/models/entities/accounts/accountـentity.py
commons_lib/models/entities/gift/__init__.py
commons_lib/models/entities/gift/redeem_entity.py
commons_lib/models/entities/gift/vended_winning_entity.py
commons_lib/models/entities/gift/winning_category_entity.py
commons_lib/models/entities/gift/winning_entity.py
commons_lib/models/entities/gift/winning_vendors.py
commons_lib/models/entities/organization/__init__.py
commons_lib/models/entities/organization/company_entity.py
commons_lib/models/entities/organization/sub_org_entity.py
commons_lib/models/entities/permissions/__init__.py
commons_lib/models/entities/permissions/permission_entity.py
commons_lib/models/entities/permissions/role_entity.py
commons_lib/models/entities/position/__init__.py
commons_lib/models/entities/position/position_category_entity.py
commons_lib/models/entities/position/position_entity.py
commons_lib/models/entities/position/positionentity.py
commons_lib/models/entities/transfers/__init__.py
commons_lib/models/entities/transfers/transaction_category_entity.py
commons_lib/models/entities/transfers/transation_entity.py
commons_lib/models/entities/transfers/transfer_category_entity.py
commons_lib/models/entities/transfers/transfer_entity.py
commons_lib/models/entities/user/__init__.py
commons_lib/models/entities/user/employee_entiry.py
commons_lib/models/entities/user/employee_entity.py
commons_lib/models/entities/user/employment_entity.py
commons_lib/models/entities/user/user_entity.py
commons_lib/models/entities/values/__init__.py
commons_lib/models/entities/values/org_behavior_entity.py
commons_lib-1.1.4.dist-info/WHEEL
commons_lib-1.1.4.dist-info/METADATA
commons_lib-1.1.4.dist-info/RECORD
