Metadata-Version: 2.1
Name: commons_lib
Version: 1.1.4
Summary: Arad PassioNikoo
Author-email: Mehdi Einali <einali@gmail.com>
Requires-Python: >=3.11
Classifier: Development Status :: 3 - Alpha
Classifier: Intended Audience :: Developers
Classifier: Programming Language :: Python :: 3.11
Requires-Dist: pydantic == 2.5.2
Requires-Dist: SQLAlchemy == 2.0.25
Requires-Dist: black==23.3.0 ; extra == "test"
Requires-Dist: check-manifest==0.49 ; extra == "test"
Requires-Dist: flake8-bugbear==23.5.9 ; extra == "test"
Requires-Dist: flake8-docstrings ; extra == "test"
Requires-Dist: flake8-formatter_junit_xml ; extra == "test"
Requires-Dist: flake8 ; extra == "test"
Requires-Dist: flake8-pyproject ; extra == "test"
Requires-Dist: pylint==2.17.4 ; extra == "test"
Requires-Dist: pylint_junit ; extra == "test"
Requires-Dist: pytest-cov==4.0.0 ; extra == "test"
Requires-Dist: pytest-mock<3.10.1 ; extra == "test"
Requires-Dist: pytest-runner ; extra == "test"
Requires-Dist: pytest==7.3.1 ; extra == "test"
Requires-Dist: shellcheck-py==0.9.0.2 ; extra == "test"
Project-URL: Documentation, https://aradsolutions.ir/
Project-URL: Source, https://aradsolutions.ir/
Project-URL: Tracker, https://aradsolutions.ir/
Provides-Extra: test
